snapstreak_revive/__init__.py
snapstreak_revive/command_line.py
snapstreak_revive/main.py
snapstreak_revive-0.0.2.dist-info/LICENSE
snapstreak_revive-0.0.2.dist-info/METADATA
snapstreak_revive-0.0.2.dist-info/WHEEL
snapstreak_revive-0.0.2.dist-info/entry_points.txt
snapstreak_revive-0.0.2.dist-info/top_level.txt
snapstreak_revive-0.0.2.dist-info/RECORD
