Metadata-Version: 2.1
Name: snapstreak-revive
Version: 0.0.2
Summary: Automatically enters required information on the Snapchat support website to retrieve snapstreaks.
Home-page: https://github.com/RoastSea8/Snapchat-Streak-Revival
Author: RoastSea8 (Aditya Tomar)
Author-email: aditya26042005@gmail.com
License: MIT
Keywords: snapchat,streaks,revive streaks,chromedriver,automation,selenium
Classifier: Development Status :: 5 - Production/Stable
Classifier: Topic :: Software Development :: Testing
Classifier: Topic :: System :: Installation/Setup
Classifier: Topic :: Software Development :: Libraries :: Python Modules
Classifier: License :: OSI Approved :: MIT License
Classifier: Programming Language :: Python :: 3
Classifier: Programming Language :: Python :: 3.6
Classifier: Programming Language :: Python :: 3.7
Classifier: Programming Language :: Python :: 3.8
Classifier: Programming Language :: Python :: 3.9
Classifier: Programming Language :: Python :: 3.10
Classifier: Operating System :: MacOS :: MacOS X
Classifier: Operating System :: Microsoft :: Windows
Requires-Python: >=3.6
License-File: LICENSE
Requires-Dist: selenium
Requires-Dist: chromedriver-autoinstall
